COPYING
COPYING.LESSER
MANIFEST.in
VERSION
requirements.txt
setup.py
tox.ini
zetup.ini
zcons/__init__.py
zcons/__main__.py
zcons/error.py
zcons/script.py
zcons/zetup_config.py
zcons.egg-info/PKG-INFO
zcons.egg-info/SOURCES.txt
zcons.egg-info/dependency_links.txt
zcons.egg-info/requires.txt
zcons.egg-info/top_level.txt