Metadata-Version: 1.1
Name: zcons
Version: 0.1rc3.dev12
Summary: Zimmermann's SCons wrapper
Home-page: https://github.com/zimmermanncode/zcons
Author: Stefan Zimmermann
Author-email: zimmermann.code@gmail.com
License: LGPLv3
Keywords: zetup,setup,scons,sconstruct,sconscript,install,installer,installation,build,builder,construct,construction,compile,compiler,compilation,zimmermann,zimmermanncode,userzimmermann,python3,python3
Platform: UNKNOWN
Classifier: Development Status :: 3 - Alpha
Classifier: Intended Audience :: Developers
Classifier: License :: OSI Approved :: GNU Library or Lesser General Public License (LGPL)
Classifier: Operating System :: OS Independent
Classifier: Topic :: Software Development
Classifier: Topic :: Utilities
Classifier: Programming Language :: Python
Classifier: Programming Language :: Python :: 2
Classifier: Programming Language :: Python :: 2.7
Classifier: Programming Language :: Python :: 3
Classifier: Programming Language :: Python :: 3.5
Classifier: Programming Language :: Python :: 3.6
Classifier: Programming Language :: Python :: 3.7
